{
  "solver": "cp_rolling",
  "solver_status": {
    "status": "FEASIBLE",
    "gap_percent": 54.0101395124,
    "day_statuses": {
      "1": {
        "status": "OPTIMAL",
        "objective": 500000.0,
        "best_bound": 500000.0,
        "gap_percent": 0.0,
        "runtime_sec": 0.8736915999998018,
        "complete_count": 0,
        "carried_over_count": 50
      },
      "2": {
        "status": "OPTIMAL",
        "objective": 735187.0,
        "best_bound": 735187.0,
        "gap_percent": 0.0,
        "runtime_sec": 1.1194316000000981,
        "complete_count": 1,
        "carried_over_count": 49
      },
      "3": {
        "status": "FEASIBLE",
        "objective": 1158774.0,
        "best_bound": 712310.0,
        "gap_percent": 38.52899702616731,
        "runtime_sec": 60.094716900000094,
        "complete_count": 18,
        "carried_over_count": 32
      },
      "4": {
        "status": "FEASIBLE",
        "objective": 1257782.0,
        "best_bound": 822300.0,
        "gap_percent": 34.62301098282532,
        "runtime_sec": 60.17426030000024,
        "complete_count": 41,
        "carried_over_count": 9
      },
      "5": {
        "status": "OPTIMAL",
        "objective": 2153737.0,
        "best_bound": 2153737.0,
        "gap_percent": 0.0,
        "runtime_sec": 32.04558610000004,
        "complete_count": 40,
        "carried_over_count": 10
      },
      "6": {
        "status": "FEASIBLE",
        "objective": 2224650.0,
        "best_bound": 1135690.0,
        "gap_percent": 48.94972242824714,
        "runtime_sec": 60.216829700000744,
        "complete_count": 46,
        "carried_over_count": 4
      },
      "7": {
        "status": "FEASIBLE",
        "objective": 2019032.0,
        "best_bound": 928550.0,
        "gap_percent": 54.0101395124,
        "runtime_sec": 60.313306199999715,
        "complete_count": 50,
        "carried_over_count": 0
      }
    }
  },
  "metrics": {
    "delivered_count": 196,
    "incomplete_count": 104,
    "total_distance_km": 684.7179016334585,
    "total_travel_time_min": 916,
    "total_waiting_time_min": 609,
    "total_service_time_min": 1477,
    "total_route_duration_min": 3002,
    "number_of_active_days": 6,
    "active_days": 6,
    "total_deferral_days": 718,
    "hard_feasible": true,
    "objective_value": 111188056.17901634,
    "violations": []
  },
  "schedule": {
    "routes": [
      {
        "day": 1,
        "return_to_depot_time": 0,
        "route_distance_km": 0.0,
        "route_travel_time_min": 0,
        "route_waiting_time_min": 0,
        "route_service_time_min": 0,
        "route_duration_min": 0,
        "hard_feasible": true,
        "violations": [],
        "stops": []
      },
      {
        "day": 2,
        "return_to_depot_time": 1291,
        "route_distance_km": 0.5175071400473621,
        "route_travel_time_min": 2,
        "route_waiting_time_min": 0,
        "route_service_time_min": 5,
        "route_duration_min": 7,
        "hard_feasible": true,
        "violations": [],
        "stops": [
          {
            "customer_id": "C169",
            "arrival_time": 1285,
            "service_start_time": 1285,
            "service_end_time": 1290,
            "selected_window_start": 1110,
            "selected_window_end": 1290,
            "travel_from_previous_min": 1,
            "waiting_min": 0,
            "distance_from_previous_km": 0.25875357002368105,
            "hard_feasible": true,
            "violation": null
          }
        ]
      },
      {
        "day": 3,
        "return_to_depot_time": 1184,
        "route_distance_km": 43.240738372324394,
        "route_travel_time_min": 61,
        "route_waiting_time_min": 173,
        "route_service_time_min": 130,
        "route_duration_min": 364,
        "hard_feasible": true,
        "violations": [],
        "stops": [
          {
            "customer_id": "C288",
            "arrival_time": 828,
            "service_start_time": 828,
            "service_end_time": 838,
            "selected_window_start": 433,
            "selected_window_end": 838,
            "travel_from_previous_min": 8,
            "waiting_min": 0,
            "distance_from_previous_km": 6.313856974148211,
            "hard_feasible": true,
            "violation": null
          },
          {
            "customer_id": "C218",
            "arrival_time": 846,
            "service_start_time": 846,
            "service_end_time": 853,
            "selected_window_start": 810,
            "selected_window_end": 1020,
            "travel_from_previous_min": 8,
            "waiting_min": 0,
            "distance_from_previous_km": 6.626586464387225,
            "hard_feasible": true,
            "violation": null
          },
          {
            "customer_id": "C245",
            "arrival_time": 854,
            "service_start_time": 854,
            "service_end_time": 861,
            "selected_window_start": 810,
            "selected_window_end": 1020,
            "travel_from_previous_min": 1,
            "waiting_min": 0,
            "distance_from_previous_km": 0.17958374091214419,
            "hard_feasible": true,
            "violation": null
          },
          {
            "customer_id": "C053",
            "arrival_time": 862,
            "service_start_time": 862,
            "service_end_time": 869,
            "selected_window_start": 810,
            "selected_window_end": 1020,
            "travel_from_previous_min": 1,
            "waiting_min": 0,
            "distance_from_previous_km": 0.6829928623345917,
            "hard_feasible": true,
            "violation": null
          },
          {
            "customer_id": "C134",
            "arrival_time": 870,
            "service_start_time": 870,
            "service_end_time": 880,
            "selected_window_start": 810,
            "selected_window_end": 1020,
            "travel_from_previous_min": 1,
            "waiting_min": 0,
            "distance_from_previous_km": 0.5244008390534866,
            "hard_feasible": true,
            "violation": null
          },
          {
            "customer_id": "C041",
            "arrival_time": 882,
            "service_start_time": 882,
            "service_end_time": 887,
            "selected_window_start": 810,
            "selected_window_end": 1020,
            "travel_from_previous_min": 2,
            "waiting_min": 0,
            "distance_from_previous_km": 1.6584591794795551,
            "hard_feasible": true,
            "violation": null
          },
          {
            "customer_id": "C194",
            "arrival_time": 890,
            "service_start_time": 890,
            "service_end_time": 895,
            "selected_window_start": 810,
            "selected_window_end": 1020,
            "travel_from_previous_min": 3,
            "waiting_min": 0,
            "distance_from_previous_km": 2.3042711862973073,
            "hard_feasible": true,
            "violation": null
          },
          {
            "customer_id": "C204",
            "arrival_time": 897,
            "service_start_time": 897,
            "service_end_time": 907,
            "selected_window_start": 810,
            "selected_window_end": 1020,
            "travel_from_previous_min": 2,
            "waiting_min": 0,
            "distance_from_previous_km": 1.3496021339639328,
            "hard_feasible": true,
            "violation": null
          },
          {
            "customer_id": "C071",
            "arrival_time": 909,
            "service_start_time": 993,
            "service_end_time": 1003,
            "selected_window_start": 810,
            "selected_window_end": 1020,
            "travel_from_previous_min": 2,
            "waiting_min": 84,
            "distance_from_previous_km": 0.951409102331904,
            "hard_feasible": true,
            "violation": null
          },
          {
            "customer_id": "C061",
            "arrival_time": 1006,
            "service_start_time": 1006,
            "service_end_time": 1011,
            "selected_window_start": 810,
            "selected_window_end": 1020,
            "travel_from_previous_min": 3,
            "waiting_min": 0,
            "distance_from_previous_km": 1.900551298965645,
            "hard_feasible": true,
            "violation": null
          },
          {
            "customer_id": "C056",
            "arrival_time": 1013,
            "service_start_time": 1013,
            "service_end_time": 1020,
            "selected_window_start": 810,
            "selected_window_end": 1020,
            "travel_from_previous_min": 2,
            "waiting_min": 0,
            "distance_from_previous_km": 1.0338968081970268,
            "hard_feasible": true,
            "violation": null
          },
          {
            "customer_id": "C116",
            "arrival_time": 1021,
            "service_start_time": 1110,
            "service_end_time": 1120,
            "selected_window_start": 1110,
            "selected_window_end": 1290,
            "travel_from_previous_min": 1,
            "waiting_min": 89,
            "distance_from_previous_km": 0.7634033272130794,
            "hard_feasible": true,
            "violation": null
          },
          {
            "customer_id": "C211",
            "arrival_time": 1123,
            "service_start_time": 1123,
            "service_end_time": 1128,
            "selected_window_start": 1110,
            "selected_window_end": 1290,
            "travel_from_previous_min": 3,
            "waiting_min": 0,
            "distance_from_previous_km": 1.6935904168363725,
            "hard_feasible": true,
            "violation": null
          },
          {
            "customer_id": "C023",
            "arrival_time": 1131,
            "service_start_time": 1131,
            "service_end_time": 1136,
            "selected_window_start": 1110,
            "selected_window_end": 1290,
            "travel_from_previous_min": 3,
            "waiting_min": 0,
            "distance_from_previous_km": 2.084563074123688,
            "hard_feasible": true,
            "violation": null
          },
          {
            "customer_id": "C114",
            "arrival_time": 1139,
            "service_start_time": 1139,
            "service_end_time": 1149,
            "selected_window_start": 1110,
            "selected_window_end": 1290,
            "travel_from_previous_min": 3,
            "waiting_min": 0,
            "distance_from_previous_km": 1.8152374307511414,
            "hard_feasible": true,
            "violation": null
          },
          {
            "customer_id": "C257",
            "arrival_time": 1150,
            "service_start_time": 1150,
            "service_end_time": 1157,
            "selected_window_start": 1110,
            "selected_window_end": 1290,
            "travel_from_previous_min": 1,
            "waiting_min": 0,
            "distance_from_previous_km": 0.40420164522178736,
            "hard_feasible": true,
            "violation": null
          },
          {
            "customer_id": "C031",
            "arrival_time": 1158,
            "service_start_time": 1158,
            "service_end_time": 1163,
            "selected_window_start": 1110,
            "selected_window_end": 1290,
            "travel_from_previous_min": 1,
            "waiting_min": 0,
            "distance_from_previous_km": 0.37919941983077976,
            "hard_feasible": true,
            "violation": null
          },
          {
            "customer_id": "C280",
            "arrival_time": 1166,
            "service_start_time": 1166,
            "service_end_time": 1171,
            "selected_window_start": 1110,
            "selected_window_end": 1290,
            "travel_from_previous_min": 3,
            "waiting_min": 0,
            "distance_from_previous_km": 2.0047912634486424,
            "hard_feasible": true,
            "violation": null
          }
        ]
      },
      {
        "day": 4,
        "return_to_depot_time": 1160,
        "route_distance_km": 102.21456559175408,
        "route_travel_time_min": 141,
        "route_waiting_time_min": 202,
        "route_service_time_min": 309,
        "route_duration_min": 652,
        "hard_feasible": true,
        "violations": [],
        "stops": [
          {
            "customer_id": "C057",
            "arrival_time": 514,
            "service_start_time": 514,
            "service_end_time": 519,
            "selected_window_start": 510,
            "selected_window_end": 690,
            "travel_from_previous_min": 6,
            "waiting_min": 0,
            "distance_from_previous_km": 4.514781308103417,
            "hard_feasible": true,
            "violation": null
          },
          {
            "customer_id": "C086",
            "arrival_time": 528,
            "service_start_time": 528,
            "service_end_time": 538,
            "selected_window_start": 510,
            "selected_window_end": 690,
            "travel_from_previous_min": 9,
            "waiting_min": 0,
            "distance_from_previous_km": 7.080326820140438,
            "hard_feasible": true,
            "violation": null
          },
          {
            "customer_id": "C055",
            "arrival_time": 539,
            "service_start_time": 539,
            "service_end_time": 544,
            "selected_window_start": 510,
            "selected_window_end": 690,
            "travel_from_previous_min": 1,
            "waiting_min": 0,
            "distance_from_previous_km": 0.135878806294433,
            "hard_feasible": true,
            "violation": null
          },
          {
            "customer_id": "C294",
            "arrival_time": 546,
            "service_start_time": 546,
            "service_end_time": 553,
            "selected_window_start": 510,
            "selected_window_end": 690,
            "travel_from_previous_min": 2,
            "waiting_min": 0,
            "distance_from_previous_km": 0.8441090095479375,
            "hard_feasible": true,
            "violation": null
          },
          {
            "customer_id": "C034",
            "arrival_time": 556,
            "service_start_time": 556,
            "service_end_time": 561,
            "selected_window_start": 510,
            "selected_window_end": 690,
            "travel_from_previous_min": 3,
            "waiting_min": 0,
            "distance_from_previous_km": 2.091003075081432,
            "hard_feasible": true,
            "violation": null
          },
          {
            "customer_id": "C297",
            "arrival_time": 562,
            "service_start_time": 562,
            "service_end_time": 569,
            "selected_window_start": 510,
            "selected_window_end": 690,
            "travel_from_previous_min": 1,
            "waiting_min": 0,
            "distance_from_previous_km": 0.5819156296234007,
            "hard_feasible": true,
            "violation": null
          },
          {
            "customer_id": "C214",
            "arrival_time": 572,
            "service_start_time": 572,
            "service_end_time": 582,
            "selected_window_start": 510,
            "selected_window_end": 690,
            "travel_from_previous_min": 3,
            "waiting_min": 0,
            "distance_from_previous_km": 2.4098277988271284,
            "hard_feasible": true,
            "violation": null
          },
          {
            "customer_id": "C038",
            "arrival_time": 611,
            "service_start_time": 611,
            "service_end_time": 621,
            "selected_window_start": 510,
            "selected_window_end": 690,
            "travel_from_previous_min": 29,
            "waiting_min": 0,
            "distance_from_previous_km": 24.11402681034422,
            "hard_feasible": true,
            "violation": null
          },
          {
            "customer_id": "C271",
            "arrival_time": 622,
            "service_start_time": 622,
            "service_end_time": 632,
            "selected_window_start": 510,
            "selected_window_end": 690,
            "travel_from_previous_min": 1,
            "waiting_min": 0,
            "distance_from_previous_km": 0.279866271637009,
            "hard_feasible": true,
            "violation": null
          },
          {
            "customer_id": "C039",
            "arrival_time": 634,
            "service_start_time": 634,
            "service_end_time": 639,
            "selected_window_start": 510,
            "selected_window_end": 690,
            "travel_from_previous_min": 2,
            "waiting_min": 0,
            "distance_from_previous_km": 1.3260791228278948,
            "hard_feasible": true,
            "violation": null
          },
          {
            "customer_id": "C260",
            "arrival_time": 640,
            "service_start_time": 640,
            "service_end_time": 647,
            "selected_window_start": 510,
            "selected_window_end": 690,
            "travel_from_previous_min": 1,
            "waiting_min": 0,
            "distance_from_previous_km": 0.8271677580757122,
            "hard_feasible": true,
            "violation": null
          },
          {
            "customer_id": "C285",
            "arrival_time": 650,
            "service_start_time": 650,
            "service_end_time": 655,
            "selected_window_start": 510,
            "selected_window_end": 690,
            "travel_from_previous_min": 3,
            "waiting_min": 0,
            "distance_from_previous_km": 2.3034990102016546,
            "hard_feasible": true,
            "violation": null
          },
          {
            "customer_id": "C124",
            "arrival_time": 656,
            "service_start_time": 656,
            "service_end_time": 661,
            "selected_window_start": 510,
            "selected_window_end": 690,
            "travel_from_previous_min": 1,
            "waiting_min": 0,
            "distance_from_previous_km": 0.6043957809250479,
            "hard_feasible": true,
            "violation": null
          },
          {
            "customer_id": "C046",
            "arrival_time": 663,
            "service_start_time": 663,
            "service_end_time": 668,
            "selected_window_start": 510,
            "selected_window_end": 690,
            "travel_from_previous_min": 2,
            "waiting_min": 0,
            "distance_from_previous_km": 1.3174906792839198,
            "hard_feasible": true,
            "violation": null
          },
          {
            "customer_id": "C223",
            "arrival_time": 672,
            "service_start_time": 672,
            "service_end_time": 682,
            "selected_window_start": 510,
            "selected_window_end": 690,
            "travel_from_previous_min": 4,
            "waiting_min": 0,
            "distance_from_previous_km": 2.7255212804159132,
            "hard_feasible": true,
            "violation": null
          },
          {
            "customer_id": "C283",
            "arrival_time": 685,
            "service_start_time": 685,
            "service_end_time": 690,
            "selected_window_start": 510,
            "selected_window_end": 690,
            "travel_from_previous_min": 3,
            "waiting_min": 0,
            "distance_from_previous_km": 2.3002066863653803,
            "hard_feasible": true,
            "violation": null
          },
          {
            "customer_id": "C063",
            "arrival_time": 703,
            "service_start_time": 810,
            "service_end_time": 820,
            "selected_window_start": 810,
            "selected_window_end": 1020,
            "travel_from_previous_min": 13,
            "waiting_min": 107,
            "distance_from_previous_km": 10.26441386392813,
            "hard_feasible": true,
            "violation": null
          },
          {
            "customer_id": "C166",
            "arrival_time": 823,
            "service_start_time": 823,
            "service_end_time": 828,
            "selected_window_start": 810,
            "selected_window_end": 1020,
            "travel_from_previous_min": 3,
            "waiting_min": 0,
            "distance_from_previous_km": 1.8648093334172262,
            "hard_feasible": true,
            "violation": null
          },
          {
            "customer_id": "C158",
            "arrival_time": 830,
            "service_start_time": 830,
            "service_end_time": 837,
            "selected_window_start": 810,
            "selected_window_end": 1020,
            "travel_from_previous_min": 2,
            "waiting_min": 0,
            "distance_from_previous_km": 1.1716386900405773,
            "hard_feasible": true,
            "violation": null
          },
          {
            "customer_id": "C096",
            "arrival_time": 840,
            "service_start_time": 840,
            "service_end_time": 850,
            "selected_window_start": 810,
            "selected_window_end": 1020,
            "travel_from_previous_min": 3,
            "waiting_min": 0,
            "distance_from_previous_km": 2.095324721851006,
            "hard_feasible": true,
            "violation": null
          },
          {
            "customer_id": "C167",
            "arrival_time": 852,
            "service_start_time": 852,
            "service_end_time": 862,
            "selected_window_start": 810,
            "selected_window_end": 1020,
            "travel_from_previous_min": 2,
            "waiting_min": 0,
            "distance_from_previous_km": 1.3778260013514039,
            "hard_feasible": true,
            "violation": null
          },
          {
            "customer_id": "C115",
            "arrival_time": 864,
            "service_start_time": 864,
            "service_end_time": 869,
            "selected_window_start": 810,
            "selected_window_end": 1020,
            "travel_from_previous_min": 2,
            "waiting_min": 0,
            "distance_from_previous_km": 1.1593441119874623,
            "hard_feasible": true,
            "violation": null
          },
          {
            "customer_id": "C030",
            "arrival_time": 870,
            "service_start_time": 870,
            "service_end_time": 877,
            "selected_window_start": 810,
            "selected_window_end": 1020,
            "travel_from_previous_min": 1,
            "waiting_min": 0,
            "distance_from_previous_km": 0.5466972562579778,
            "hard_feasible": true,
            "violation": null
          },
          {
            "customer_id": "C265",
            "arrival_time": 878,
            "service_start_time": 878,
            "service_end_time": 888,
            "selected_window_start": 810,
            "selected_window_end": 1020,
            "travel_from_previous_min": 1,
            "waiting_min": 0,
            "distance_from_previous_km": 0.5665656625670141,
            "hard_feasible": true,
            "violation": null
          },
          {
            "customer_id": "C069",
            "arrival_time": 890,
            "service_start_time": 890,
            "service_end_time": 895,
            "selected_window_start": 810,
            "selected_window_end": 1020,
            "travel_from_previous_min": 2,
            "waiting_min": 0,
            "distance_from_previous_km": 0.8968887612184687,
            "hard_feasible": true,
            "violation": null
          },
          {
            "customer_id": "C291",
            "arrival_time": 896,
            "service_start_time": 896,
            "service_end_time": 903,
            "selected_window_start": 810,
            "selected_window_end": 1020,
            "travel_from_previous_min": 1,
            "waiting_min": 0,
            "distance_from_previous_km": 0.2403973793534364,
            "hard_feasible": true,
            "violation": null
          },
          {
            "customer_id": "C229",
            "arrival_time": 904,
            "service_start_time": 904,
            "service_end_time": 914,
            "selected_window_start": 810,
            "selected_window_end": 1020,
            "travel_from_previous_min": 1,
            "waiting_min": 0,
            "distance_from_previous_km": 0.15559562975867788,
            "hard_feasible": true,
            "violation": null
          },
          {
            "customer_id": "C081",
            "arrival_time": 915,
            "service_start_time": 915,
            "service_end_time": 922,
            "selected_window_start": 810,
            "selected_window_end": 1020,
            "travel_from_previous_min": 1,
            "waiting_min": 0,
            "distance_from_previous_km": 0.8026309550472115,
            "hard_feasible": true,
            "violation": null
          },
          {
            "customer_id": "C059",
            "arrival_time": 923,
            "service_start_time": 923,
            "service_end_time": 930,
            "selected_window_start": 810,
            "selected_window_end": 1020,
            "travel_from_previous_min": 1,
            "waiting_min": 0,
            "distance_from_previous_km": 0.44785848211237456,
            "hard_feasible": true,
            "violation": null
          },
          {
            "customer_id": "C129",
            "arrival_time": 932,
            "service_start_time": 932,
            "service_end_time": 942,
            "selected_window_start": 810,
            "selected_window_end": 1020,
            "travel_from_previous_min": 2,
            "waiting_min": 0,
            "distance_from_previous_km": 1.444059534783798,
            "hard_feasible": true,
            "violation": null
          },
          {
            "customer_id": "C174",
            "arrival_time": 943,
            "service_start_time": 943,
            "service_end_time": 953,
            "selected_window_start": 810,
            "selected_window_end": 1020,
            "travel_from_previous_min": 1,
            "waiting_min": 0,
            "distance_from_previous_km": 0.7091470933452376,
            "hard_feasible": true,
            "violation": null
          },
          {
            "customer_id": "C054",
            "arrival_time": 954,
            "service_start_time": 954,
            "service_end_time": 964,
            "selected_window_start": 810,
            "selected_window_end": 1020,
            "travel_from_previous_min": 1,
            "waiting_min": 0,
            "distance_from_previous_km": 0.4784908985550287,
            "hard_feasible": true,
            "violation": null
          },
          {
            "customer_id": "C143",
            "arrival_time": 966,
            "service_start_time": 966,
            "service_end_time": 973,
            "selected_window_start": 810,
            "selected_window_end": 1020,
            "travel_from_previous_min": 2,
            "waiting_min": 0,
            "distance_from_previous_km": 1.4293503769195295,
            "hard_feasible": true,
            "violation": null
          },
          {
            "customer_id": "C150",
            "arrival_time": 975,
            "service_start_time": 975,
            "service_end_time": 985,
            "selected_window_start": 810,
            "selected_window_end": 1020,
            "travel_from_previous_min": 2,
            "waiting_min": 0,
            "distance_from_previous_km": 1.2446924158200687,
            "hard_feasible": true,
            "violation": null
          },
          {
            "customer_id": "C243",
            "arrival_time": 986,
            "service_start_time": 986,
            "service_end_time": 993,
            "selected_window_start": 810,
            "selected_window_end": 1020,
            "travel_from_previous_min": 1,
            "waiting_min": 0,
            "distance_from_previous_km": 0.7594098366494868,
            "hard_feasible": true,
            "violation": null
          },
          {
            "customer_id": "C152",
            "arrival_time": 994,
            "service_start_time": 994,
            "service_end_time": 999,
            "selected_window_start": 810,
            "selected_window_end": 1020,
            "travel_from_previous_min": 1,
            "waiting_min": 0,
            "distance_from_previous_km": 0.7299368739829485,
            "hard_feasible": true,
            "violation": null
          },
          {
            "customer_id": "C060",
            "arrival_time": 1000,
            "service_start_time": 1006,
            "service_end_time": 1011,
            "selected_window_start": 810,
            "selected_window_end": 1020,
            "travel_from_previous_min": 1,
            "waiting_min": 6,
            "distance_from_previous_km": 0.38345049224117694,
            "hard_feasible": true,
            "violation": null
          },
          {
            "customer_id": "C084",
            "arrival_time": 1013,
            "service_start_time": 1013,
            "service_end_time": 1020,
            "selected_window_start": 810,
            "selected_window_end": 1020,
            "travel_from_previous_min": 2,
            "waiting_min": 0,
            "distance_from_previous_km": 1.5132837969131891,
            "hard_feasible": true,
            "violation": null
          },
          {
            "customer_id": "C168",
            "arrival_time": 1021,
            "service_start_time": 1110,
            "service_end_time": 1120,
            "selected_window_start": 1110,
            "selected_window_end": 1290,
            "travel_from_previous_min": 1,
            "waiting_min": 89,
            "distance_from_previous_km": 0.13609559140545308,
            "hard_feasible": true,
            "violation": null
          },
          {
            "customer_id": "C270",
            "arrival_time": 1122,
            "service_start_time": 1122,
            "service_end_time": 1132,
            "selected_window_start": 1110,
            "selected_window_end": 1290,
            "travel_from_previous_min": 2,
            "waiting_min": 0,
            "distance_from_previous_km": 1.458305262967943,
            "hard_feasible": true,
            "violation": null
          },
          {
            "customer_id": "C278",
            "arrival_time": 1136,
            "service_start_time": 1136,
            "service_end_time": 1143,
            "selected_window_start": 1110,
            "selected_window_end": 1290,
            "travel_from_previous_min": 4,
            "waiting_min": 0,
            "distance_from_previous_km": 3.2415879102686693,
            "hard_feasible": true,
            "violation": null
          }
        ]
      },
      {
        "day": 5,
        "return_to_depot_time": 1250,
        "route_distance_km": 150.49962541431452,
        "route_travel_time_min": 203,
        "route_waiting_time_min": 234,
        "route_service_time_min": 300,
        "route_duration_min": 737,
        "hard_feasible": true,
        "violations": [],
        "stops": [
          {
            "customer_id": "C140",
            "arrival_time": 517,
            "service_start_time": 517,
            "service_end_time": 522,
            "selected_window_start": 425,
            "selected_window_end": 861,
            "travel_from_previous_min": 4,
            "waiting_min": 0,
            "distance_from_previous_km": 2.5786096040308237,
            "hard_feasible": true,
            "violation": null
          },
          {
            "customer_id": "C171",
            "arrival_time": 538,
            "service_start_time": 538,
            "service_end_time": 548,
            "selected_window_start": 510,
            "selected_window_end": 690,
            "travel_from_previous_min": 16,
            "waiting_min": 0,
            "distance_from_previous_km": 12.710583250976331,
            "hard_feasible": true,
            "violation": null
          },
          {
            "customer_id": "C072",
            "arrival_time": 552,
            "service_start_time": 552,
            "service_end_time": 562,
            "selected_window_start": 510,
            "selected_window_end": 690,
            "travel_from_previous_min": 4,
            "waiting_min": 0,
            "distance_from_previous_km": 2.9143088391589522,
            "hard_feasible": true,
            "violation": null
          },
          {
            "customer_id": "C156",
            "arrival_time": 567,
            "service_start_time": 567,
            "service_end_time": 572,
            "selected_window_start": 510,
            "selected_window_end": 690,
            "travel_from_previous_min": 5,
            "waiting_min": 0,
            "distance_from_previous_km": 3.9795173890812436,
            "hard_feasible": true,
            "violation": null
          },
          {
            "customer_id": "C130",
            "arrival_time": 579,
            "service_start_time": 579,
            "service_end_time": 586,
            "selected_window_start": 510,
            "selected_window_end": 690,
            "travel_from_previous_min": 7,
            "waiting_min": 0,
            "distance_from_previous_km": 5.1498786509975165,
            "hard_feasible": true,
            "violation": null
          },
          {
            "customer_id": "C002",
            "arrival_time": 591,
            "service_start_time": 591,
            "service_end_time": 596,
            "selected_window_start": 510,
            "selected_window_end": 690,
            "travel_from_previous_min": 5,
            "waiting_min": 0,
            "distance_from_previous_km": 3.637550121991449,
            "hard_feasible": true,
            "violation": null
          },
          {
            "customer_id": "C122",
            "arrival_time": 599,
            "service_start_time": 599,
            "service_end_time": 604,
            "selected_window_start": 510,
            "selected_window_end": 690,
            "travel_from_previous_min": 3,
            "waiting_min": 0,
            "distance_from_previous_km": 1.9421579570158556,
            "hard_feasible": true,
            "violation": null
          },
          {
            "customer_id": "C276",
            "arrival_time": 606,
            "service_start_time": 606,
            "service_end_time": 611,
            "selected_window_start": 510,
            "selected_window_end": 690,
            "travel_from_previous_min": 2,
            "waiting_min": 0,
            "distance_from_previous_km": 0.9024331831221625,
            "hard_feasible": true,
            "violation": null
          },
          {
            "customer_id": "C017",
            "arrival_time": 614,
            "service_start_time": 614,
            "service_end_time": 624,
            "selected_window_start": 457,
            "selected_window_end": 852,
            "travel_from_previous_min": 3,
            "waiting_min": 0,
            "distance_from_previous_km": 1.667313413848758,
            "hard_feasible": true,
            "violation": null
          },
          {
            "customer_id": "C015",
            "arrival_time": 626,
            "service_start_time": 626,
            "service_end_time": 631,
            "selected_window_start": 509,
            "selected_window_end": 1107,
            "travel_from_previous_min": 2,
            "waiting_min": 0,
            "distance_from_previous_km": 1.3878707504663397,
            "hard_feasible": true,
            "violation": null
          },
          {
            "customer_id": "C008",
            "arrival_time": 650,
            "service_start_time": 650,
            "service_end_time": 660,
            "selected_window_start": 510,
            "selected_window_end": 690,
            "travel_from_previous_min": 19,
            "waiting_min": 0,
            "distance_from_previous_km": 15.156083972451459,
            "hard_feasible": true,
            "violation": null
          },
          {
            "customer_id": "C228",
            "arrival_time": 665,
            "service_start_time": 665,
            "service_end_time": 675,
            "selected_window_start": 510,
            "selected_window_end": 690,
            "travel_from_previous_min": 5,
            "waiting_min": 0,
            "distance_from_previous_km": 4.123744630793715,
            "hard_feasible": true,
            "violation": null
          },
          {
            "customer_id": "C247",
            "arrival_time": 685,
            "service_start_time": 685,
            "service_end_time": 690,
            "selected_window_start": 510,
            "selected_window_end": 690,
            "travel_from_previous_min": 10,
            "waiting_min": 0,
            "distance_from_previous_km": 8.305430758846889,
            "hard_feasible": true,
            "violation": null
          },
          {
            "customer_id": "C119",
            "arrival_time": 696,
            "service_start_time": 810,
            "service_end_time": 817,
            "selected_window_start": 810,
            "selected_window_end": 1020,
            "travel_from_previous_min": 6,
            "waiting_min": 114,
            "distance_from_previous_km": 4.925010152273801,
            "hard_feasible": true,
            "violation": null
          },
          {
            "customer_id": "C144",
            "arrival_time": 821,
            "service_start_time": 821,
            "service_end_time": 828,
            "selected_window_start": 434,
            "selected_window_end": 829,
            "travel_from_previous_min": 4,
            "waiting_min": 0,
            "distance_from_previous_km": 3.170028646558262,
            "hard_feasible": true,
            "violation": null
          },
          {
            "customer_id": "C236",
            "arrival_time": 830,
            "service_start_time": 830,
            "service_end_time": 835,
            "selected_window_start": 810,
            "selected_window_end": 1020,
            "travel_from_previous_min": 2,
            "waiting_min": 0,
            "distance_from_previous_km": 1.6251559094437678,
            "hard_feasible": true,
            "violation": null
          },
          {
            "customer_id": "C217",
            "arrival_time": 837,
            "service_start_time": 837,
            "service_end_time": 844,
            "selected_window_start": 583,
            "selected_window_end": 1111,
            "travel_from_previous_min": 2,
            "waiting_min": 0,
            "distance_from_previous_km": 0.9519334693139007,
            "hard_feasible": true,
            "violation": null
          },
          {
            "customer_id": "C192",
            "arrival_time": 847,
            "service_start_time": 847,
            "service_end_time": 854,
            "selected_window_start": 810,
            "selected_window_end": 1020,
            "travel_from_previous_min": 3,
            "waiting_min": 0,
            "distance_from_previous_km": 1.913077868253146,
            "hard_feasible": true,
            "violation": null
          },
          {
            "customer_id": "C203",
            "arrival_time": 856,
            "service_start_time": 856,
            "service_end_time": 861,
            "selected_window_start": 810,
            "selected_window_end": 1020,
            "travel_from_previous_min": 2,
            "waiting_min": 0,
            "distance_from_previous_km": 1.3086071450209953,
            "hard_feasible": true,
            "violation": null
          },
          {
            "customer_id": "C300",
            "arrival_time": 877,
            "service_start_time": 877,
            "service_end_time": 887,
            "selected_window_start": 441,
            "selected_window_end": 949,
            "travel_from_previous_min": 16,
            "waiting_min": 0,
            "distance_from_previous_km": 13.050311910831864,
            "hard_feasible": true,
            "violation": null
          },
          {
            "customer_id": "C098",
            "arrival_time": 889,
            "service_start_time": 889,
            "service_end_time": 896,
            "selected_window_start": 810,
            "selected_window_end": 1020,
            "travel_from_previous_min": 2,
            "waiting_min": 0,
            "distance_from_previous_km": 1.2771764639234473,
            "hard_feasible": true,
            "violation": null
          },
          {
            "customer_id": "C221",
            "arrival_time": 898,
            "service_start_time": 898,
            "service_end_time": 908,
            "selected_window_start": 810,
            "selected_window_end": 1020,
            "travel_from_previous_min": 2,
            "waiting_min": 0,
            "distance_from_previous_km": 1.206515234052187,
            "hard_feasible": true,
            "violation": null
          },
          {
            "customer_id": "C010",
            "arrival_time": 910,
            "service_start_time": 910,
            "service_end_time": 915,
            "selected_window_start": 810,
            "selected_window_end": 1020,
            "travel_from_previous_min": 2,
            "waiting_min": 0,
            "distance_from_previous_km": 0.9137240830797884,
            "hard_feasible": true,
            "violation": null
          },
          {
            "customer_id": "C255",
            "arrival_time": 918,
            "service_start_time": 918,
            "service_end_time": 923,
            "selected_window_start": 810,
            "selected_window_end": 1020,
            "travel_from_previous_min": 3,
            "waiting_min": 0,
            "distance_from_previous_km": 1.723495250936306,
            "hard_feasible": true,
            "violation": null
          },
          {
            "customer_id": "C006",
            "arrival_time": 926,
            "service_start_time": 926,
            "service_end_time": 933,
            "selected_window_start": 810,
            "selected_window_end": 1020,
            "travel_from_previous_min": 3,
            "waiting_min": 0,
            "distance_from_previous_km": 1.9000413679707082,
            "hard_feasible": true,
            "violation": null
          },
          {
            "customer_id": "C232",
            "arrival_time": 935,
            "service_start_time": 935,
            "service_end_time": 940,
            "selected_window_start": 810,
            "selected_window_end": 1020,
            "travel_from_previous_min": 2,
            "waiting_min": 0,
            "distance_from_previous_km": 1.4284960097949182,
            "hard_feasible": true,
            "violation": null
          },
          {
            "customer_id": "C183",
            "arrival_time": 941,
            "service_start_time": 941,
            "service_end_time": 946,
            "selected_window_start": 810,
            "selected_window_end": 1020,
            "travel_from_previous_min": 1,
            "waiting_min": 0,
            "distance_from_previous_km": 0.217071877496835,
            "hard_feasible": true,
            "violation": null
          },
          {
            "customer_id": "C242",
            "arrival_time": 950,
            "service_start_time": 950,
            "service_end_time": 960,
            "selected_window_start": 810,
            "selected_window_end": 1020,
            "travel_from_previous_min": 4,
            "waiting_min": 0,
            "distance_from_previous_km": 3.0656771193326935,
            "hard_feasible": true,
            "violation": null
          },
          {
            "customer_id": "C239",
            "arrival_time": 964,
            "service_start_time": 964,
            "service_end_time": 974,
            "selected_window_start": 810,
            "selected_window_end": 1020,
            "travel_from_previous_min": 4,
            "waiting_min": 0,
            "distance_from_previous_km": 3.0182192846113747,
            "hard_feasible": true,
            "violation": null
          },
          {
            "customer_id": "C070",
            "arrival_time": 975,
            "service_start_time": 975,
            "service_end_time": 982,
            "selected_window_start": 810,
            "selected_window_end": 1020,
            "travel_from_previous_min": 1,
            "waiting_min": 0,
            "distance_from_previous_km": 0.6077932625490358,
            "hard_feasible": true,
            "violation": null
          },
          {
            "customer_id": "C241",
            "arrival_time": 984,
            "service_start_time": 984,
            "service_end_time": 989,
            "selected_window_start": 810,
            "selected_window_end": 1020,
            "travel_from_previous_min": 2,
            "waiting_min": 0,
            "distance_from_previous_km": 0.9946775004995325,
            "hard_feasible": true,
            "violation": null
          },
          {
            "customer_id": "C268",
            "arrival_time": 990,
            "service_start_time": 1110,
            "service_end_time": 1120,
            "selected_window_start": 1110,
            "selected_window_end": 1290,
            "travel_from_previous_min": 1,
            "waiting_min": 120,
            "distance_from_previous_km": 0.543451018952031,
            "hard_feasible": true,
            "violation": null
          },
          {
            "customer_id": "C235",
            "arrival_time": 1122,
            "service_start_time": 1122,
            "service_end_time": 1132,
            "selected_window_start": 1110,
            "selected_window_end": 1290,
            "travel_from_previous_min": 2,
            "waiting_min": 0,
            "distance_from_previous_km": 1.0958067758505596,
            "hard_feasible": true,
            "violation": null
          },
          {
            "customer_id": "C295",
            "arrival_time": 1134,
            "service_start_time": 1134,
            "service_end_time": 1141,
            "selected_window_start": 1110,
            "selected_window_end": 1290,
            "travel_from_previous_min": 2,
            "waiting_min": 0,
            "distance_from_previous_km": 1.369125564000614,
            "hard_feasible": true,
            "violation": null
          },
          {
            "customer_id": "C095",
            "arrival_time": 1143,
            "service_start_time": 1143,
            "service_end_time": 1153,
            "selected_window_start": 1110,
            "selected_window_end": 1290,
            "travel_from_previous_min": 2,
            "waiting_min": 0,
            "distance_from_previous_km": 1.0244687452528736,
            "hard_feasible": true,
            "violation": null
          },
          {
            "customer_id": "C007",
            "arrival_time": 1156,
            "service_start_time": 1156,
            "service_end_time": 1166,
            "selected_window_start": 1110,
            "selected_window_end": 1290,
            "travel_from_previous_min": 3,
            "waiting_min": 0,
            "distance_from_previous_km": 1.8705504858196162,
            "hard_feasible": true,
            "violation": null
          },
          {
            "customer_id": "C091",
            "arrival_time": 1170,
            "service_start_time": 1170,
            "service_end_time": 1177,
            "selected_window_start": 1110,
            "selected_window_end": 1290,
            "travel_from_previous_min": 4,
            "waiting_min": 0,
            "distance_from_previous_km": 2.6367036712531804,
            "hard_feasible": true,
            "violation": null
          },
          {
            "customer_id": "C163",
            "arrival_time": 1198,
            "service_start_time": 1198,
            "service_end_time": 1208,
            "selected_window_start": 1110,
            "selected_window_end": 1290,
            "travel_from_previous_min": 21,
            "waiting_min": 0,
            "distance_from_previous_km": 16.80377399782561,
            "hard_feasible": true,
            "violation": null
          },
          {
            "customer_id": "C180",
            "arrival_time": 1210,
            "service_start_time": 1210,
            "service_end_time": 1220,
            "selected_window_start": 1110,
            "selected_window_end": 1290,
            "travel_from_previous_min": 2,
            "waiting_min": 0,
            "distance_from_previous_km": 1.3201395570166057,
            "hard_feasible": true,
            "violation": null
          },
          {
            "customer_id": "C131",
            "arrival_time": 1224,
            "service_start_time": 1224,
            "service_end_time": 1234,
            "selected_window_start": 1110,
            "selected_window_end": 1290,
            "travel_from_previous_min": 4,
            "waiting_min": 0,
            "distance_from_previous_km": 2.7826334379504623,
            "hard_feasible": true,
            "violation": null
          }
        ]
      },
      {
        "day": 6,
        "return_to_depot_time": 1037,
        "route_distance_km": 181.40772644821104,
        "route_travel_time_min": 238,
        "route_waiting_time_min": 0,
        "route_service_time_min": 332,
        "route_duration_min": 570,
        "hard_feasible": true,
        "violations": [],
        "stops": [
          {
            "customer_id": "C121",
            "arrival_time": 480,
            "service_start_time": 480,
            "service_end_time": 487,
            "selected_window_start": 480,
            "selected_window_end": 1260,
            "travel_from_previous_min": 13,
            "waiting_min": 0,
            "distance_from_previous_km": 10.433517776857428,
            "hard_feasible": true,
            "violation": null
          },
          {
            "customer_id": "C148",
            "arrival_time": 498,
            "service_start_time": 498,
            "service_end_time": 508,
            "selected_window_start": 477,
            "selected_window_end": 913,
            "travel_from_previous_min": 11,
            "waiting_min": 0,
            "distance_from_previous_km": 8.894751209561738,
            "hard_feasible": true,
            "violation": null
          },
          {
            "customer_id": "C009",
            "arrival_time": 510,
            "service_start_time": 510,
            "service_end_time": 520,
            "selected_window_start": 480,
            "selected_window_end": 1260,
            "travel_from_previous_min": 2,
            "waiting_min": 0,
            "distance_from_previous_km": 1.2700225588547633,
            "hard_feasible": true,
            "violation": null
          },
          {
            "customer_id": "C272",
            "arrival_time": 523,
            "service_start_time": 523,
            "service_end_time": 528,
            "selected_window_start": 480,
            "selected_window_end": 1260,
            "travel_from_previous_min": 3,
            "waiting_min": 0,
            "distance_from_previous_km": 2.3228398696423316,
            "hard_feasible": true,
            "violation": null
          },
          {
            "customer_id": "C065",
            "arrival_time": 531,
            "service_start_time": 531,
            "service_end_time": 536,
            "selected_window_start": 480,
            "selected_window_end": 1260,
            "travel_from_previous_min": 3,
            "waiting_min": 0,
            "distance_from_previous_km": 2.3603382130533754,
            "hard_feasible": true,
            "violation": null
          },
          {
            "customer_id": "C024",
            "arrival_time": 537,
            "service_start_time": 537,
            "service_end_time": 544,
            "selected_window_start": 425,
            "selected_window_end": 884,
            "travel_from_previous_min": 1,
            "waiting_min": 0,
            "distance_from_previous_km": 0.7162921889843564,
            "hard_feasible": true,
            "violation": null
          },
          {
            "customer_id": "C237",
            "arrival_time": 545,
            "service_start_time": 545,
            "service_end_time": 550,
            "selected_window_start": 480,
            "selected_window_end": 1260,
            "travel_from_previous_min": 1,
            "waiting_min": 0,
            "distance_from_previous_km": 0.817123980800956,
            "hard_feasible": true,
            "violation": null
          },
          {
            "customer_id": "C181",
            "arrival_time": 551,
            "service_start_time": 551,
            "service_end_time": 556,
            "selected_window_start": 480,
            "selected_window_end": 1260,
            "travel_from_previous_min": 1,
            "waiting_min": 0,
            "distance_from_previous_km": 0.6716824547358676,
            "hard_feasible": true,
            "violation": null
          },
          {
            "customer_id": "C033",
            "arrival_time": 558,
            "service_start_time": 558,
            "service_end_time": 568,
            "selected_window_start": 446,
            "selected_window_end": 826,
            "travel_from_previous_min": 2,
            "waiting_min": 0,
            "distance_from_previous_km": 1.0920253660057542,
            "hard_feasible": true,
            "violation": null
          },
          {
            "customer_id": "C051",
            "arrival_time": 569,
            "service_start_time": 569,
            "service_end_time": 579,
            "selected_window_start": 480,
            "selected_window_end": 1260,
            "travel_from_previous_min": 1,
            "waiting_min": 0,
            "distance_from_previous_km": 0.3044531162593017,
            "hard_feasible": true,
            "violation": null
          },
          {
            "customer_id": "C105",
            "arrival_time": 580,
            "service_start_time": 580,
            "service_end_time": 585,
            "selected_window_start": 480,
            "selected_window_end": 1260,
            "travel_from_previous_min": 1,
            "waiting_min": 0,
            "distance_from_previous_km": 0.5077582594109139,
            "hard_feasible": true,
            "violation": null
          },
          {
            "customer_id": "C036",
            "arrival_time": 596,
            "service_start_time": 596,
            "service_end_time": 601,
            "selected_window_start": 480,
            "selected_window_end": 1260,
            "travel_from_previous_min": 11,
            "waiting_min": 0,
            "distance_from_previous_km": 8.963918634726667,
            "hard_feasible": true,
            "violation": null
          },
          {
            "customer_id": "C198",
            "arrival_time": 617,
            "service_start_time": 617,
            "service_end_time": 624,
            "selected_window_start": 421,
            "selected_window_end": 882,
            "travel_from_previous_min": 16,
            "waiting_min": 0,
            "distance_from_previous_km": 13.033505994167495,
            "hard_feasible": true,
            "violation": null
          },
          {
            "customer_id": "C137",
            "arrival_time": 635,
            "service_start_time": 635,
            "service_end_time": 642,
            "selected_window_start": 480,
            "selected_window_end": 1260,
            "travel_from_previous_min": 11,
            "waiting_min": 0,
            "distance_from_previous_km": 8.637617097903798,
            "hard_feasible": true,
            "violation": null
          },
          {
            "customer_id": "C044",
            "arrival_time": 654,
            "service_start_time": 654,
            "service_end_time": 659,
            "selected_window_start": 467,
            "selected_window_end": 954,
            "travel_from_previous_min": 12,
            "waiting_min": 0,
            "distance_from_previous_km": 9.251089632037948,
            "hard_feasible": true,
            "violation": null
          },
          {
            "customer_id": "C157",
            "arrival_time": 663,
            "service_start_time": 663,
            "service_end_time": 673,
            "selected_window_start": 480,
            "selected_window_end": 1260,
            "travel_from_previous_min": 4,
            "waiting_min": 0,
            "distance_from_previous_km": 2.742208256132271,
            "hard_feasible": true,
            "violation": null
          },
          {
            "customer_id": "C135",
            "arrival_time": 675,
            "service_start_time": 675,
            "service_end_time": 685,
            "selected_window_start": 437,
            "selected_window_end": 1036,
            "travel_from_previous_min": 2,
            "waiting_min": 0,
            "distance_from_previous_km": 1.3047795254371526,
            "hard_feasible": true,
            "violation": null
          },
          {
            "customer_id": "C179",
            "arrival_time": 687,
            "service_start_time": 687,
            "service_end_time": 692,
            "selected_window_start": 504,
            "selected_window_end": 1008,
            "travel_from_previous_min": 2,
            "waiting_min": 0,
            "distance_from_previous_km": 1.6520033958802884,
            "hard_feasible": true,
            "violation": null
          },
          {
            "customer_id": "C062",
            "arrival_time": 693,
            "service_start_time": 693,
            "service_end_time": 700,
            "selected_window_start": 480,
            "selected_window_end": 1260,
            "travel_from_previous_min": 1,
            "waiting_min": 0,
            "distance_from_previous_km": 0.2875399450511187,
            "hard_feasible": true,
            "violation": null
          },
          {
            "customer_id": "C107",
            "arrival_time": 701,
            "service_start_time": 701,
            "service_end_time": 708,
            "selected_window_start": 433,
            "selected_window_end": 818,
            "travel_from_previous_min": 1,
            "waiting_min": 0,
            "distance_from_previous_km": 0.17144086444019077,
            "hard_feasible": true,
            "violation": null
          },
          {
            "customer_id": "C153",
            "arrival_time": 711,
            "service_start_time": 711,
            "service_end_time": 716,
            "selected_window_start": 480,
            "selected_window_end": 1260,
            "travel_from_previous_min": 3,
            "waiting_min": 0,
            "distance_from_previous_km": 1.6863028701867284,
            "hard_feasible": true,
            "violation": null
          },
          {
            "customer_id": "C299",
            "arrival_time": 720,
            "service_start_time": 720,
            "service_end_time": 725,
            "selected_window_start": 480,
            "selected_window_end": 1260,
            "travel_from_previous_min": 4,
            "waiting_min": 0,
            "distance_from_previous_km": 2.590892689788599,
            "hard_feasible": true,
            "violation": null
          },
          {
            "customer_id": "C066",
            "arrival_time": 743,
            "service_start_time": 743,
            "service_end_time": 748,
            "selected_window_start": 480,
            "selected_window_end": 1260,
            "travel_from_previous_min": 18,
            "waiting_min": 0,
            "distance_from_previous_km": 14.27400771507428,
            "hard_feasible": true,
            "violation": null
          },
          {
            "customer_id": "C089",
            "arrival_time": 749,
            "service_start_time": 749,
            "service_end_time": 756,
            "selected_window_start": 480,
            "selected_window_end": 1260,
            "travel_from_previous_min": 1,
            "waiting_min": 0,
            "distance_from_previous_km": 0.615169114959456,
            "hard_feasible": true,
            "violation": null
          },
          {
            "customer_id": "C025",
            "arrival_time": 758,
            "service_start_time": 758,
            "service_end_time": 763,
            "selected_window_start": 505,
            "selected_window_end": 899,
            "travel_from_previous_min": 2,
            "waiting_min": 0,
            "distance_from_previous_km": 1.4259625941798062,
            "hard_feasible": true,
            "violation": null
          },
          {
            "customer_id": "C275",
            "arrival_time": 766,
            "service_start_time": 766,
            "service_end_time": 776,
            "selected_window_start": 531,
            "selected_window_end": 920,
            "travel_from_previous_min": 3,
            "waiting_min": 0,
            "distance_from_previous_km": 2.114572933242077,
            "hard_feasible": true,
            "violation": null
          },
          {
            "customer_id": "C123",
            "arrival_time": 781,
            "service_start_time": 781,
            "service_end_time": 786,
            "selected_window_start": 480,
            "selected_window_end": 1260,
            "travel_from_previous_min": 5,
            "waiting_min": 0,
            "distance_from_previous_km": 3.4541651451544695,
            "hard_feasible": true,
            "violation": null
          },
          {
            "customer_id": "C165",
            "arrival_time": 787,
            "service_start_time": 787,
            "service_end_time": 797,
            "selected_window_start": 480,
            "selected_window_end": 1260,
            "travel_from_previous_min": 1,
            "waiting_min": 0,
            "distance_from_previous_km": 0.7419690155255814,
            "hard_feasible": true,
            "violation": null
          },
          {
            "customer_id": "C254",
            "arrival_time": 800,
            "service_start_time": 800,
            "service_end_time": 807,
            "selected_window_start": 439,
            "selected_window_end": 832,
            "travel_from_previous_min": 3,
            "waiting_min": 0,
            "distance_from_previous_km": 1.8089768959276404,
            "hard_feasible": true,
            "violation": null
          },
          {
            "customer_id": "C225",
            "arrival_time": 808,
            "service_start_time": 808,
            "service_end_time": 818,
            "selected_window_start": 480,
            "selected_window_end": 1260,
            "travel_from_previous_min": 1,
            "waiting_min": 0,
            "distance_from_previous_km": 0.8010719068847691,
            "hard_feasible": true,
            "violation": null
          },
          {
            "customer_id": "C282",
            "arrival_time": 821,
            "service_start_time": 821,
            "service_end_time": 826,
            "selected_window_start": 480,
            "selected_window_end": 1260,
            "travel_from_previous_min": 3,
            "waiting_min": 0,
            "distance_from_previous_km": 2.353474650383981,
            "hard_feasible": true,
            "violation": null
          },
          {
            "customer_id": "C172",
            "arrival_time": 827,
            "service_start_time": 827,
            "service_end_time": 837,
            "selected_window_start": 480,
            "selected_window_end": 1260,
            "travel_from_previous_min": 1,
            "waiting_min": 0,
            "distance_from_previous_km": 0.7597765066123078,
            "hard_feasible": true,
            "violation": null
          },
          {
            "customer_id": "C248",
            "arrival_time": 839,
            "service_start_time": 839,
            "service_end_time": 849,
            "selected_window_start": 480,
            "selected_window_end": 1260,
            "travel_from_previous_min": 2,
            "waiting_min": 0,
            "distance_from_previous_km": 1.5004126499066845,
            "hard_feasible": true,
            "violation": null
          },
          {
            "customer_id": "C101",
            "arrival_time": 851,
            "service_start_time": 851,
            "service_end_time": 856,
            "selected_window_start": 576,
            "selected_window_end": 1059,
            "travel_from_previous_min": 2,
            "waiting_min": 0,
            "distance_from_previous_km": 1.5425512373986163,
            "hard_feasible": true,
            "violation": null
          },
          {
            "customer_id": "C159",
            "arrival_time": 878,
            "service_start_time": 878,
            "service_end_time": 888,
            "selected_window_start": 480,
            "selected_window_end": 1260,
            "travel_from_previous_min": 22,
            "waiting_min": 0,
            "distance_from_previous_km": 17.812368934254646,
            "hard_feasible": true,
            "violation": null
          },
          {
            "customer_id": "C227",
            "arrival_time": 893,
            "service_start_time": 893,
            "service_end_time": 898,
            "selected_window_start": 500,
            "selected_window_end": 1075,
            "travel_from_previous_min": 5,
            "waiting_min": 0,
            "distance_from_previous_km": 3.5933474045797476,
            "hard_feasible": true,
            "violation": null
          },
          {
            "customer_id": "C263",
            "arrival_time": 903,
            "service_start_time": 903,
            "service_end_time": 913,
            "selected_window_start": 480,
            "selected_window_end": 1260,
            "travel_from_previous_min": 5,
            "waiting_min": 0,
            "distance_from_previous_km": 3.8407457882551914,
            "hard_feasible": true,
            "violation": null
          },
          {
            "customer_id": "C067",
            "arrival_time": 926,
            "service_start_time": 926,
            "service_end_time": 931,
            "selected_window_start": 480,
            "selected_window_end": 1260,
            "travel_from_previous_min": 13,
            "waiting_min": 0,
            "distance_from_previous_km": 10.431015881974297,
            "hard_feasible": true,
            "violation": null
          },
          {
            "customer_id": "C018",
            "arrival_time": 933,
            "service_start_time": 933,
            "service_end_time": 943,
            "selected_window_start": 480,
            "selected_window_end": 1260,
            "travel_from_previous_min": 2,
            "waiting_min": 0,
            "distance_from_previous_km": 1.458829153807943,
            "hard_feasible": true,
            "violation": null
          },
          {
            "customer_id": "C207",
            "arrival_time": 944,
            "service_start_time": 944,
            "service_end_time": 951,
            "selected_window_start": 480,
            "selected_window_end": 1260,
            "travel_from_previous_min": 1,
            "waiting_min": 0,
            "distance_from_previous_km": 0.5203654485071033,
            "hard_feasible": true,
            "violation": null
          },
          {
            "customer_id": "C177",
            "arrival_time": 965,
            "service_start_time": 965,
            "service_end_time": 970,
            "selected_window_start": 480,
            "selected_window_end": 1260,
            "travel_from_previous_min": 14,
            "waiting_min": 0,
            "distance_from_previous_km": 11.462204275356465,
            "hard_feasible": true,
            "violation": null
          },
          {
            "customer_id": "C176",
            "arrival_time": 972,
            "service_start_time": 972,
            "service_end_time": 979,
            "selected_window_start": 537,
            "selected_window_end": 1041,
            "travel_from_previous_min": 2,
            "waiting_min": 0,
            "distance_from_previous_km": 1.4399700691333839,
            "hard_feasible": true,
            "violation": null
          },
          {
            "customer_id": "C274",
            "arrival_time": 981,
            "service_start_time": 981,
            "service_end_time": 988,
            "selected_window_start": 582,
            "selected_window_end": 1137,
            "travel_from_previous_min": 2,
            "waiting_min": 0,
            "distance_from_previous_km": 1.1979165455072411,
            "hard_feasible": true,
            "violation": null
          },
          {
            "customer_id": "C139",
            "arrival_time": 989,
            "service_start_time": 989,
            "service_end_time": 999,
            "selected_window_start": 480,
            "selected_window_end": 1260,
            "travel_from_previous_min": 1,
            "waiting_min": 0,
            "distance_from_previous_km": 0.6618296608644869,
            "hard_feasible": true,
            "violation": null
          },
          {
            "customer_id": "C125",
            "arrival_time": 1004,
            "service_start_time": 1004,
            "service_end_time": 1014,
            "selected_window_start": 480,
            "selected_window_end": 1260,
            "travel_from_previous_min": 5,
            "waiting_min": 0,
            "distance_from_previous_km": 3.4315202185037457,
            "hard_feasible": true,
            "violation": null
          },
          {
            "customer_id": "C209",
            "arrival_time": 1016,
            "service_start_time": 1016,
            "service_end_time": 1021,
            "selected_window_start": 480,
            "selected_window_end": 1260,
            "travel_from_previous_min": 2,
            "waiting_min": 0,
            "distance_from_previous_km": 1.384013356149426,
            "hard_feasible": true,
            "violation": null
          }
        ]
      },
      {
        "day": 7,
        "return_to_depot_time": 1121,
        "route_distance_km": 206.83773866680707,
        "route_travel_time_min": 271,
        "route_waiting_time_min": 0,
        "route_service_time_min": 401,
        "route_duration_min": 672,
        "hard_feasible": true,
        "violations": [],
        "stops": [
          {
            "customer_id": "C110",
            "arrival_time": 466,
            "service_start_time": 466,
            "service_end_time": 476,
            "selected_window_start": 465,
            "selected_window_end": 1064,
            "travel_from_previous_min": 17,
            "waiting_min": 0,
            "distance_from_previous_km": 13.610902308076419,
            "hard_feasible": true,
            "violation": null
          },
          {
            "customer_id": "C264",
            "arrival_time": 480,
            "service_start_time": 480,
            "service_end_time": 485,
            "selected_window_start": 468,
            "selected_window_end": 1019,
            "travel_from_previous_min": 4,
            "waiting_min": 0,
            "distance_from_previous_km": 2.5979003772277345,
            "hard_feasible": true,
            "violation": null
          },
          {
            "customer_id": "C005",
            "arrival_time": 488,
            "service_start_time": 488,
            "service_end_time": 495,
            "selected_window_start": 445,
            "selected_window_end": 934,
            "travel_from_previous_min": 3,
            "waiting_min": 0,
            "distance_from_previous_km": 2.114994404247917,
            "hard_feasible": true,
            "violation": null
          },
          {
            "customer_id": "C216",
            "arrival_time": 497,
            "service_start_time": 497,
            "service_end_time": 504,
            "selected_window_start": 482,
            "selected_window_end": 974,
            "travel_from_previous_min": 2,
            "waiting_min": 0,
            "distance_from_previous_km": 1.471809501939705,
            "hard_feasible": true,
            "violation": null
          },
          {
            "customer_id": "C231",
            "arrival_time": 506,
            "service_start_time": 506,
            "service_end_time": 513,
            "selected_window_start": 493,
            "selected_window_end": 896,
            "travel_from_previous_min": 2,
            "waiting_min": 0,
            "distance_from_previous_km": 1.3484647752166148,
            "hard_feasible": true,
            "violation": null
          },
          {
            "customer_id": "C100",
            "arrival_time": 516,
            "service_start_time": 516,
            "service_end_time": 521,
            "selected_window_start": 516,
            "selected_window_end": 956,
            "travel_from_previous_min": 3,
            "waiting_min": 0,
            "distance_from_previous_km": 2.1332517174492094,
            "hard_feasible": true,
            "violation": null
          },
          {
            "customer_id": "C187",
            "arrival_time": 524,
            "service_start_time": 524,
            "service_end_time": 534,
            "selected_window_start": 519,
            "selected_window_end": 960,
            "travel_from_previous_min": 3,
            "waiting_min": 0,
            "distance_from_previous_km": 1.8103960229739797,
            "hard_feasible": true,
            "violation": null
          },
          {
            "customer_id": "C068",
            "arrival_time": 537,
            "service_start_time": 537,
            "service_end_time": 544,
            "selected_window_start": 526,
            "selected_window_end": 1009,
            "travel_from_previous_min": 3,
            "waiting_min": 0,
            "distance_from_previous_km": 1.8234222111184228,
            "hard_feasible": true,
            "violation": null
          },
          {
            "customer_id": "C246",
            "arrival_time": 561,
            "service_start_time": 561,
            "service_end_time": 571,
            "selected_window_start": 514,
            "selected_window_end": 990,
            "travel_from_previous_min": 17,
            "waiting_min": 0,
            "distance_from_previous_km": 13.7176825163728,
            "hard_feasible": true,
            "violation": null
          },
          {
            "customer_id": "C266",
            "arrival_time": 575,
            "service_start_time": 575,
            "service_end_time": 582,
            "selected_window_start": 513,
            "selected_window_end": 1012,
            "travel_from_previous_min": 4,
            "waiting_min": 0,
            "distance_from_previous_km": 2.545298198639993,
            "hard_feasible": true,
            "violation": null
          },
          {
            "customer_id": "C258",
            "arrival_time": 609,
            "service_start_time": 609,
            "service_end_time": 616,
            "selected_window_start": 462,
            "selected_window_end": 934,
            "travel_from_previous_min": 27,
            "waiting_min": 0,
            "distance_from_previous_km": 21.77065458685154,
            "hard_feasible": true,
            "violation": null
          },
          {
            "customer_id": "C252",
            "arrival_time": 618,
            "service_start_time": 618,
            "service_end_time": 625,
            "selected_window_start": 433,
            "selected_window_end": 894,
            "travel_from_previous_min": 2,
            "waiting_min": 0,
            "distance_from_previous_km": 1.1963548177693752,
            "hard_feasible": true,
            "violation": null
          },
          {
            "customer_id": "C230",
            "arrival_time": 633,
            "service_start_time": 633,
            "service_end_time": 640,
            "selected_window_start": 462,
            "selected_window_end": 843,
            "travel_from_previous_min": 8,
            "waiting_min": 0,
            "distance_from_previous_km": 6.0798599802956,
            "hard_feasible": true,
            "violation": null
          },
          {
            "customer_id": "C201",
            "arrival_time": 643,
            "service_start_time": 643,
            "service_end_time": 648,
            "selected_window_start": 482,
            "selected_window_end": 925,
            "travel_from_previous_min": 3,
            "waiting_min": 0,
            "distance_from_previous_km": 2.284539831125735,
            "hard_feasible": true,
            "violation": null
          },
          {
            "customer_id": "C184",
            "arrival_time": 652,
            "service_start_time": 652,
            "service_end_time": 659,
            "selected_window_start": 439,
            "selected_window_end": 886,
            "travel_from_previous_min": 4,
            "waiting_min": 0,
            "distance_from_previous_km": 2.610446676337213,
            "hard_feasible": true,
            "violation": null
          },
          {
            "customer_id": "C284",
            "arrival_time": 670,
            "service_start_time": 670,
            "service_end_time": 680,
            "selected_window_start": 423,
            "selected_window_end": 845,
            "travel_from_previous_min": 11,
            "waiting_min": 0,
            "distance_from_previous_km": 8.446098376173463,
            "hard_feasible": true,
            "violation": null
          },
          {
            "customer_id": "C249",
            "arrival_time": 681,
            "service_start_time": 681,
            "service_end_time": 691,
            "selected_window_start": 560,
            "selected_window_end": 1067,
            "travel_from_previous_min": 1,
            "waiting_min": 0,
            "distance_from_previous_km": 0.7324022119027227,
            "hard_feasible": true,
            "violation": null
          },
          {
            "customer_id": "C182",
            "arrival_time": 692,
            "service_start_time": 692,
            "service_end_time": 699,
            "selected_window_start": 439,
            "selected_window_end": 875,
            "travel_from_previous_min": 1,
            "waiting_min": 0,
            "distance_from_previous_km": 0.759640684797753,
            "hard_feasible": true,
            "violation": null
          },
          {
            "customer_id": "C141",
            "arrival_time": 700,
            "service_start_time": 700,
            "service_end_time": 710,
            "selected_window_start": 424,
            "selected_window_end": 845,
            "travel_from_previous_min": 1,
            "waiting_min": 0,
            "distance_from_previous_km": 0.4214074156917499,
            "hard_feasible": true,
            "violation": null
          },
          {
            "customer_id": "C147",
            "arrival_time": 716,
            "service_start_time": 716,
            "service_end_time": 721,
            "selected_window_start": 593,
            "selected_window_end": 1062,
            "travel_from_previous_min": 6,
            "waiting_min": 0,
            "distance_from_previous_km": 4.425084543825124,
            "hard_feasible": true,
            "violation": null
          },
          {
            "customer_id": "C251",
            "arrival_time": 724,
            "service_start_time": 724,
            "service_end_time": 734,
            "selected_window_start": 536,
            "selected_window_end": 896,
            "travel_from_previous_min": 3,
            "waiting_min": 0,
            "distance_from_previous_km": 2.3557077259286645,
            "hard_feasible": true,
            "violation": null
          },
          {
            "customer_id": "C112",
            "arrival_time": 736,
            "service_start_time": 736,
            "service_end_time": 746,
            "selected_window_start": 546,
            "selected_window_end": 1133,
            "travel_from_previous_min": 2,
            "waiting_min": 0,
            "distance_from_previous_km": 1.1048674943177588,
            "hard_feasible": true,
            "violation": null
          },
          {
            "customer_id": "C205",
            "arrival_time": 748,
            "service_start_time": 748,
            "service_end_time": 755,
            "selected_window_start": 484,
            "selected_window_end": 1012,
            "travel_from_previous_min": 2,
            "waiting_min": 0,
            "distance_from_previous_km": 1.2398899830226868,
            "hard_feasible": true,
            "violation": null
          },
          {
            "customer_id": "C003",
            "arrival_time": 757,
            "service_start_time": 757,
            "service_end_time": 764,
            "selected_window_start": 452,
            "selected_window_end": 983,
            "travel_from_previous_min": 2,
            "waiting_min": 0,
            "distance_from_previous_km": 0.9462873242308593,
            "hard_feasible": true,
            "violation": null
          },
          {
            "customer_id": "C224",
            "arrival_time": 765,
            "service_start_time": 765,
            "service_end_time": 775,
            "selected_window_start": 449,
            "selected_window_end": 855,
            "travel_from_previous_min": 1,
            "waiting_min": 0,
            "distance_from_previous_km": 0.8093447843780794,
            "hard_feasible": true,
            "violation": null
          },
          {
            "customer_id": "C094",
            "arrival_time": 776,
            "service_start_time": 776,
            "service_end_time": 783,
            "selected_window_start": 480,
            "selected_window_end": 1260,
            "travel_from_previous_min": 1,
            "waiting_min": 0,
            "distance_from_previous_km": 0.6975606066858988,
            "hard_feasible": true,
            "violation": null
          },
          {
            "customer_id": "C035",
            "arrival_time": 784,
            "service_start_time": 784,
            "service_end_time": 791,
            "selected_window_start": 480,
            "selected_window_end": 1260,
            "travel_from_previous_min": 1,
            "waiting_min": 0,
            "distance_from_previous_km": 0.7325877763107981,
            "hard_feasible": true,
            "violation": null
          },
          {
            "customer_id": "C019",
            "arrival_time": 793,
            "service_start_time": 793,
            "service_end_time": 803,
            "selected_window_start": 480,
            "selected_window_end": 1260,
            "travel_from_previous_min": 2,
            "waiting_min": 0,
            "distance_from_previous_km": 1.5658271200870162,
            "hard_feasible": true,
            "violation": null
          },
          {
            "customer_id": "C013",
            "arrival_time": 804,
            "service_start_time": 804,
            "service_end_time": 814,
            "selected_window_start": 446,
            "selected_window_end": 988,
            "travel_from_previous_min": 1,
            "waiting_min": 0,
            "distance_from_previous_km": 0.5877610398793036,
            "hard_feasible": true,
            "violation": null
          },
          {
            "customer_id": "C027",
            "arrival_time": 815,
            "service_start_time": 815,
            "service_end_time": 825,
            "selected_window_start": 480,
            "selected_window_end": 1260,
            "travel_from_previous_min": 1,
            "waiting_min": 0,
            "distance_from_previous_km": 0.7004701992233499,
            "hard_feasible": true,
            "violation": null
          },
          {
            "customer_id": "C075",
            "arrival_time": 851,
            "service_start_time": 851,
            "service_end_time": 861,
            "selected_window_start": 551,
            "selected_window_end": 1030,
            "travel_from_previous_min": 26,
            "waiting_min": 0,
            "distance_from_previous_km": 21.28575107366428,
            "hard_feasible": true,
            "violation": null
          },
          {
            "customer_id": "C126",
            "arrival_time": 864,
            "service_start_time": 864,
            "service_end_time": 869,
            "selected_window_start": 560,
            "selected_window_end": 1153,
            "travel_from_previous_min": 3,
            "waiting_min": 0,
            "distance_from_previous_km": 1.955707086963689,
            "hard_feasible": true,
            "violation": null
          },
          {
            "customer_id": "C032",
            "arrival_time": 870,
            "service_start_time": 870,
            "service_end_time": 880,
            "selected_window_start": 514,
            "selected_window_end": 1110,
            "travel_from_previous_min": 1,
            "waiting_min": 0,
            "distance_from_previous_km": 0.20974846840919015,
            "hard_feasible": true,
            "violation": null
          },
          {
            "customer_id": "C092",
            "arrival_time": 882,
            "service_start_time": 882,
            "service_end_time": 889,
            "selected_window_start": 448,
            "selected_window_end": 914,
            "travel_from_previous_min": 2,
            "waiting_min": 0,
            "distance_from_previous_km": 1.303840469536053,
            "hard_feasible": true,
            "violation": null
          },
          {
            "customer_id": "C052",
            "arrival_time": 890,
            "service_start_time": 890,
            "service_end_time": 895,
            "selected_window_start": 576,
            "selected_window_end": 1162,
            "travel_from_previous_min": 1,
            "waiting_min": 0,
            "distance_from_previous_km": 0.6588620872382929,
            "hard_feasible": true,
            "violation": null
          },
          {
            "customer_id": "C215",
            "arrival_time": 896,
            "service_start_time": 896,
            "service_end_time": 906,
            "selected_window_start": 541,
            "selected_window_end": 925,
            "travel_from_previous_min": 1,
            "waiting_min": 0,
            "distance_from_previous_km": 0.7481859996017018,
            "hard_feasible": true,
            "violation": null
          },
          {
            "customer_id": "C021",
            "arrival_time": 910,
            "service_start_time": 910,
            "service_end_time": 915,
            "selected_window_start": 527,
            "selected_window_end": 1050,
            "travel_from_previous_min": 4,
            "waiting_min": 0,
            "distance_from_previous_km": 3.1012489822650484,
            "hard_feasible": true,
            "violation": null
          },
          {
            "customer_id": "C256",
            "arrival_time": 919,
            "service_start_time": 919,
            "service_end_time": 929,
            "selected_window_start": 442,
            "selected_window_end": 989,
            "travel_from_previous_min": 4,
            "waiting_min": 0,
            "distance_from_previous_km": 3.145827515932809,
            "hard_feasible": true,
            "violation": null
          },
          {
            "customer_id": "C160",
            "arrival_time": 931,
            "service_start_time": 931,
            "service_end_time": 938,
            "selected_window_start": 445,
            "selected_window_end": 1010,
            "travel_from_previous_min": 2,
            "waiting_min": 0,
            "distance_from_previous_km": 1.3498960293296667,
            "hard_feasible": true,
            "violation": null
          },
          {
            "customer_id": "C022",
            "arrival_time": 942,
            "service_start_time": 942,
            "service_end_time": 952,
            "selected_window_start": 590,
            "selected_window_end": 1121,
            "travel_from_previous_min": 4,
            "waiting_min": 0,
            "distance_from_previous_km": 3.0928642663395363,
            "hard_feasible": true,
            "violation": null
          },
          {
            "customer_id": "C161",
            "arrival_time": 953,
            "service_start_time": 953,
            "service_end_time": 958,
            "selected_window_start": 526,
            "selected_window_end": 961,
            "travel_from_previous_min": 1,
            "waiting_min": 0,
            "distance_from_previous_km": 0.7801154786312081,
            "hard_feasible": true,
            "violation": null
          },
          {
            "customer_id": "C178",
            "arrival_time": 966,
            "service_start_time": 966,
            "service_end_time": 976,
            "selected_window_start": 561,
            "selected_window_end": 1042,
            "travel_from_previous_min": 8,
            "waiting_min": 0,
            "distance_from_previous_km": 6.486555395585549,
            "hard_feasible": true,
            "violation": null
          },
          {
            "customer_id": "C206",
            "arrival_time": 990,
            "service_start_time": 990,
            "service_end_time": 997,
            "selected_window_start": 549,
            "selected_window_end": 1145,
            "travel_from_previous_min": 14,
            "waiting_min": 0,
            "distance_from_previous_km": 11.395154045470383,
            "hard_feasible": true,
            "violation": null
          },
          {
            "customer_id": "C103",
            "arrival_time": 1000,
            "service_start_time": 1000,
            "service_end_time": 1010,
            "selected_window_start": 480,
            "selected_window_end": 1260,
            "travel_from_previous_min": 3,
            "waiting_min": 0,
            "distance_from_previous_km": 2.3624166546145062,
            "hard_feasible": true,
            "violation": null
          },
          {
            "customer_id": "C145",
            "arrival_time": 1024,
            "service_start_time": 1024,
            "service_end_time": 1031,
            "selected_window_start": 480,
            "selected_window_end": 1260,
            "travel_from_previous_min": 14,
            "waiting_min": 0,
            "distance_from_previous_km": 11.147392722067345,
            "hard_feasible": true,
            "violation": null
          },
          {
            "customer_id": "C200",
            "arrival_time": 1043,
            "service_start_time": 1043,
            "service_end_time": 1053,
            "selected_window_start": 480,
            "selected_window_end": 1260,
            "travel_from_previous_min": 12,
            "waiting_min": 0,
            "distance_from_previous_km": 9.387346571316092,
            "hard_feasible": true,
            "violation": null
          },
          {
            "customer_id": "C011",
            "arrival_time": 1063,
            "service_start_time": 1063,
            "service_end_time": 1068,
            "selected_window_start": 480,
            "selected_window_end": 1260,
            "travel_from_previous_min": 10,
            "waiting_min": 0,
            "distance_from_previous_km": 8.130037190566842,
            "hard_feasible": true,
            "violation": null
          },
          {
            "customer_id": "C290",
            "arrival_time": 1070,
            "service_start_time": 1070,
            "service_end_time": 1080,
            "selected_window_start": 480,
            "selected_window_end": 1260,
            "travel_from_previous_min": 2,
            "waiting_min": 0,
            "distance_from_previous_km": 1.1532154178643288,
            "hard_feasible": true,
            "violation": null
          },
          {
            "customer_id": "C286",
            "arrival_time": 1081,
            "service_start_time": 1081,
            "service_end_time": 1091,
            "selected_window_start": 480,
            "selected_window_end": 1260,
            "travel_from_previous_min": 1,
            "waiting_min": 0,
            "distance_from_previous_km": 0.41599675479503423,
            "hard_feasible": true,
            "violation": null
          },
          {
            "customer_id": "C189",
            "arrival_time": 1108,
            "service_start_time": 1108,
            "service_end_time": 1118,
            "selected_window_start": 480,
            "selected_window_end": 1260,
            "travel_from_previous_min": 17,
            "waiting_min": 0,
            "distance_from_previous_km": 13.61918953242079,
            "hard_feasible": true,
            "violation": null
          }
        ]
      }
    ]
  }
}